pp.py
pp_ez-0.2.0.dist-info/DESCRIPTION.rst
pp_ez-0.2.0.dist-info/METADATA
pp_ez-0.2.0.dist-info/metadata.json
pp_ez-0.2.0.dist-info/RECORD
pp_ez-0.2.0.dist-info/top_level.txt
pp_ez-0.2.0.dist-info/WHEEL
