Metadata-Version: 2.0
Name: pp-ez
Version: 0.2.0
Summary: A short alias for the pprintpp or pprint module
Home-page: https://github.com/wolever/pprintpp
Author: David Wolever
Author-email: david@wolever.net
License: BSD
Platform: UNKNOWN
Classifier: Development Status :: 3 - Alpha
Classifier: Environment :: Console
Classifier: Intended Audience :: Developers
Classifier: License :: OSI Approved :: BSD License
Classifier: Natural Language :: English
Classifier: Operating System :: OS Independent
Classifier: Programming Language :: Python
Classifier: Programming Language :: Python :: 2
Classifier: Programming Language :: Python :: 3
Classifier: Topic :: Software Development
Classifier: Topic :: Utilities
